{
    "titulo": "ANTES DE DONAR",
    "recomendaciones": [
        {
            "numero": 1,
            "descripcion": "Beber mucho líquido 24 h antes."
        },
        {
            "numero": 2,
            "descripcion": "Evitar ejercicio intenso 3-4 h antes."
        },
        {
            "numero": 3,
            "descripcion": "Comer algo salado en las 3-4 h antes."
        },
        {
            "numero": 4,
            "descripcion": "Beber 3 vasos de agua las 3-4 h antes."
        }
    ],
    "Imagen": "img/AntesDeDonar.png"
}