{
  "slides": [
    {
      "image": "img/carrusel/Imagen 1.png",
      "title": "¿Quieres saber si podes donar?",
      "buttonText": "realizar el test",
      "buttonColor": "bg-blue-600 hover:bg-blue-700"
    },
    {
      "image": "img/carrusel/Imagen 2.png",
      "title": "Tu donación salva vidas",
      "buttonText": "Donar ahora",
      "buttonColor": "bg-red-600 hover:bg-red-700"
    },
    {
      "image": "img/carrusel/Imagen 3.png",
      "title": "Únete a nuestra misión",
      "buttonText": "Saber más",
      "buttonColor": "bg-green-600 hover:bg-green-700"
    }
  ]
}